README.txt
__init__.py
setup.cfg
setup.py
MiscMod.egg-info/PKG-INFO
MiscMod.egg-info/SOURCES.txt
MiscMod.egg-info/dependency_links.txt
MiscMod.egg-info/top_level.txt
cpu/__init__.py
cpu/lol/__init__.py
mathy/__init__.py
mathy/add.py
test/__init__.py