Metadata-Version: 1.0
Name: MiscMod
Version: 0.2
Summary: Random modules in a package, becuase why not?
Home-page: UNKNOWN
Author: MrCobalt
Author-email: anemail@idontwanttotellyou.com
License: UNKNOWN
Platform: UNKNOWN
